interface_py/__init__.py
interface_py/_internals/__init__.py
interface_py/_internals/core.py
interface_py/_internals/core_api.py
interface_py/_internals/helper_functions.py
interface_py-1.5.0.dist-info/METADATA
interface_py-1.5.0.dist-info/WHEEL
interface_py-1.5.0.dist-info/top_level.txt
interface_py-1.5.0.dist-info/RECORD
