Metadata-Version: 2.4
Name: interface-py
Version: 1.5.0
Summary: A package to define interface in Python
Home-page: https://github.com/ehsankarbasian/interface-py
Author: Ehsan Karbasian
Author-email: ehsan.karbasian@gmail.com
Classifier: Programming Language :: Python :: 3
Classifier: License :: OSI Approved :: MIT License
Classifier: Operating System :: OS Independent
Requires-Python: >=3.6
Dynamic: author
Dynamic: author-email
Dynamic: classifier
Dynamic: description
Dynamic: description-content-type
Dynamic: home-page
Dynamic: requires-python
Dynamic: summary
